functai/__init__.py
functai/core.py
functai/module.py
functai-0.12.0.dist-info/METADATA
functai-0.12.0.dist-info/WHEEL
functai-0.12.0.dist-info/licenses/LICENSE
functai-0.12.0.dist-info/RECORD
