Metadata-Version: 2.4
Name: functai
Version: 0.12.0
Summary: DSPy-powered function decorators for AI-enhanced programming
Project-URL: Homepage, https://github.com/maximerivest/functai
Project-URL: Bug Tracker, https://github.com/maximerivest/functai/issues
Project-URL: Documentation, https://github.com/maximerivest/functai#readme
Project-URL: Source, https://github.com/maximerivest/functai
Author-email: Maxime Rivest <maxime.rivest@gmail.com>
License: MIT
License-File: LICENSE
Keywords: ai,artificial-intelligence,decorators,dspy,function-decorators,llm,machine-learning,prompt-engineering
Classifier: Development Status :: 3 - Alpha
Classifier: Intended Audience :: Developers
Classifier: License :: OSI Approved :: MIT License
Classifier: Programming Language :: Python :: 3
Classifier: Programming Language :: Python :: 3.10
Classifier: Programming Language :: Python :: 3.11
Classifier: Programming Language :: Python :: 3.12
Classifier: Programming Language :: Python :: 3.13
Classifier: Topic :: Scientific/Engineering :: Artificial Intelligence
Classifier: Topic :: Software Development :: Libraries :: Python Modules
Requires-Python: >=3.10
Requires-Dist: dspy>=3.0.2
Requires-Dist: typing>=3.10.0.0
Provides-Extra: dev
Requires-Dist: mypy>=1.0.0; extra == 'dev'
Requires-Dist: pytest-cov>=4.0.0; extra == 'dev'
Requires-Dist: pytest>=7.0.0; extra == 'dev'
Requires-Dist: ruff>=0.1.0; extra == 'dev'
